<annotationInfo>
<item  id="470" filename="batch_align2d_hls/align2d.c" linenumber="135" name="exitcond3" contextFuncName="batch_align2D" moduleName="batch_align2D" rtlName="exitcond3_fu_1889_p2" latency="0" BRAM="-1" DSP="-1" FF="0" LUT="20" fileDirectory="/home/dmalvezzi/batch_align2d/hls"><\/item>
<item  id="472" filename="batch_align2d_hls/align2d.c" linenumber="135" name="indvar_next" contextFuncName="batch_align2D" moduleName="batch_align2D" rtlName="indvar_next_fu_1895_p2" latency="0" BRAM="-1" DSP="-1" FF="0" LUT="26" fileDirectory="/home/dmalvezzi/batch_align2d/hls"><\/item>
<item  id="478" filename="batch_align2d_hls/align2d.c" linenumber="135" name="indvar4" contextFuncName="batch_align2D" moduleName="batch_align2D" rtlName="indvar4_fu_1901_p1" latency="0" BRAM="-1" DSP="-1" FF="-1" LUT="-1" fileDirectory="/home/dmalvezzi/batch_align2d/hls"><\/item>
<item  id="493" filename="batch_align2d_hls/align2d.c" linenumber="137" name="exitcond1" contextFuncName="batch_align2D" moduleName="batch_align2D" rtlName="exitcond1_fu_1906_p2" latency="0" BRAM="-1" DSP="-1" FF="0" LUT="13" fileDirectory="/home/dmalvezzi/batch_align2d/hls"><\/item>
<item  id="495" filename="batch_align2d_hls/align2d.c" linenumber="137" name="indvar_next1" contextFuncName="batch_align2D" moduleName="batch_align2D" rtlName="indvar_next1_fu_1912_p2" latency="0" BRAM="-1" DSP="-1" FF="0" LUT="16" fileDirectory="/home/dmalvezzi/batch_align2d/hls"><\/item>
<item  id="503" filename="batch_align2d_hls/align2d.c" linenumber="137" name="div_t" contextFuncName="batch_align2D" moduleName="batch_align2D" rtlName="div_t_reg_10129" latency="0" BRAM="-1" DSP="-1" FF="-1" LUT="-1" fileDirectory="/home/dmalvezzi/batch_align2d/hls"><\/item>
<item  id="504" filename="batch_align2d_hls/align2d.c" linenumber="137" name="tmp" contextFuncName="batch_align2D" moduleName="batch_align2D" rtlName="tmp_fu_1934_p1" latency="0" BRAM="-1" DSP="-1" FF="-1" LUT="-1" fileDirectory="/home/dmalvezzi/batch_align2d/hls"><\/item>
<item  id="1733" filename="batch_align2d_hls/align2d.c" linenumber="138" name="exitcond2" contextFuncName="batch_align2D" moduleName="batch_align2D" rtlName="exitcond2_fu_4358_p2" latency="0" BRAM="-1" DSP="-1" FF="0" LUT="11" fileDirectory="/home/dmalvezzi/batch_align2d/hls"><\/item>
<item  id="1735" filename="batch_align2d_hls/align2d.c" linenumber="138" name="indvar_next2" contextFuncName="batch_align2D" moduleName="batch_align2D" rtlName="indvar_next2_fu_4364_p2" latency="0" BRAM="-1" DSP="-1" FF="0" LUT="12" fileDirectory="/home/dmalvezzi/batch_align2d/hls"><\/item>
<item  id="1742" filename="batch_align2d_hls/align2d.c" linenumber="138" name="p_t2" contextFuncName="batch_align2D" moduleName="batch_align2D" rtlName="p_t2_reg_10151" latency="0" BRAM="-1" DSP="-1" FF="-1" LUT="-1" fileDirectory="/home/dmalvezzi/batch_align2d/hls"><\/item>
<item  id="1743" filename="batch_align2d_hls/align2d.c" linenumber="138" name="tmp_61" contextFuncName="batch_align2D" moduleName="batch_align2D" rtlName="tmp_61_fu_4380_p1" latency="0" BRAM="-1" DSP="-1" FF="-1" LUT="-1" fileDirectory="/home/dmalvezzi/batch_align2d/hls"><\/item>
<item  id="1829" filename="batch_align2d_hls/align2d.c" linenumber="151" name="exitcond" contextFuncName="batch_align2D" moduleName="batch_align2D" rtlName="exitcond_fu_4432_p2" latency="0" BRAM="-1" DSP="-1" FF="0" LUT="9" fileDirectory="/home/dmalvezzi/batch_align2d/hls"><\/item>
<item  id="1831" filename="batch_align2d_hls/align2d.c" linenumber="151" name="k_1" contextFuncName="batch_align2D" moduleName="batch_align2D" rtlName="k_1_fu_4438_p2" latency="0" BRAM="-1" DSP="-1" FF="0" LUT="11" fileDirectory="/home/dmalvezzi/batch_align2d/hls"><\/item>
<item  id="1836" filename="batch_align2d_hls/align2d.c" linenumber="157" name="tmp_7" contextFuncName="batch_align2D" moduleName="batch_align2D" rtlName="tmp_7_fu_4444_p1" latency="0" BRAM="-1" DSP="-1" FF="-1" LUT="-1" fileDirectory="/home/dmalvezzi/batch_align2d/hls"><\/item>
<item  id="1837" filename="batch_align2d_hls/align2d.c" linenumber="157" name="tmp_79" contextFuncName="batch_align2D" moduleName="batch_align2D" rtlName="tmp_79_fu_4448_p1" latency="0" BRAM="-1" DSP="-1" FF="-1" LUT="-1" fileDirectory="/home/dmalvezzi/batch_align2d/hls"><\/item>
<item  id="1838" filename="batch_align2d_hls/align2d.c" linenumber="33" name="tmp_8" contextFuncName="compute_inverse_hessian" moduleName="batch_align2D" rtlName="tmp_9_fu_4456_p10" latency="0" BRAM="-1" DSP="-1" FF="-1" LUT="-1" fileDirectory="/home/dmalvezzi/batch_align2d/hls"><\/item>
<item  id="1839" filename="batch_align2d_hls/align2d.c" linenumber="33" name="tmp_9" contextFuncName="compute_inverse_hessian" moduleName="batch_align2D" rtlName="tmp_9_fu_4456_p2" latency="0" BRAM="-1" DSP="0" FF="0" LUT="30" fileDirectory="/home/dmalvezzi/batch_align2d/hls"><\/item>
<item  id="1848" filename="batch_align2d_hls/align2d.c" linenumber="23" name="exitcond_i" contextFuncName="compute_inverse_hessian" moduleName="batch_align2D" rtlName="exitcond_i_fu_4462_p2" latency="0" BRAM="-1" DSP="-1" FF="0" LUT="11" fileDirectory="/home/dmalvezzi/batch_align2d/hls"><\/item>
<item  id="1850" filename="batch_align2d_hls/align2d.c" linenumber="23" name="i" contextFuncName="compute_inverse_hessian" moduleName="batch_align2D" rtlName="i_fu_4468_p2" latency="0" BRAM="-1" DSP="-1" FF="0" LUT="15" fileDirectory="/home/dmalvezzi/batch_align2d/hls"><\/item>
<item  id="1854" filename="batch_align2d_hls/align2d.c" linenumber="33" name="tmp_82" contextFuncName="compute_inverse_hessian" moduleName="batch_align2D" rtlName="tmp_82_fu_4474_p1" latency="0" BRAM="-1" DSP="-1" FF="-1" LUT="-1" fileDirectory="/home/dmalvezzi/batch_align2d/hls"><\/item>
<item  id="1855" filename="batch_align2d_hls/align2d.c" linenumber="23" name="tmp_78" contextFuncName="compute_inverse_hessian" moduleName="batch_align2D" rtlName="tmp_78_fu_4478_p4" latency="0" BRAM="-1" DSP="-1" FF="-1" LUT="-1" fileDirectory="/home/dmalvezzi/batch_align2d/hls"><\/item>
<item  id="1856" filename="batch_align2d_hls/align2d.c" linenumber="33" name="tmp_35" contextFuncName="compute_inverse_hessian" moduleName="batch_align2D" rtlName="tmp_35_fu_4488_p3" latency="0" BRAM="-1" DSP="-1" FF="-1" LUT="-1" fileDirectory="/home/dmalvezzi/batch_align2d/hls"><\/item>
<item  id="1857" filename="batch_align2d_hls/align2d.c" linenumber="33" name="tmp_45_cast" contextFuncName="compute_inverse_hessian" moduleName="batch_align2D" rtlName="tmp_45_cast_fu_4496_p1" latency="0" BRAM="-1" DSP="-1" FF="-1" LUT="-1" fileDirectory="/home/dmalvezzi/batch_align2d/hls"><\/item>
<item  id="1858" filename="batch_align2d_hls/align2d.c" linenumber="33" name="tmp_36" contextFuncName="compute_inverse_hessian" moduleName="batch_align2D" rtlName="tmp_36_fu_4500_p3" latency="0" BRAM="-1" DSP="-1" FF="-1" LUT="-1" fileDirectory="/home/dmalvezzi/batch_align2d/hls"><\/item>
<item  id="1859" filename="batch_align2d_hls/align2d.c" linenumber="33" name="tmp_47_cast" contextFuncName="compute_inverse_hessian" moduleName="batch_align2D" rtlName="tmp_47_cast_fu_4508_p1" latency="0" BRAM="-1" DSP="-1" FF="-1" LUT="-1" fileDirectory="/home/dmalvezzi/batch_align2d/hls"><\/item>
<item  id="1860" filename="batch_align2d_hls/align2d.c" linenumber="33" name="tmp_37" contextFuncName="compute_inverse_hessian" moduleName="batch_align2D" rtlName="tmp_37_fu_4512_p2" latency="0" BRAM="-1" DSP="-1" FF="0" LUT="15" fileDirectory="/home/dmalvezzi/batch_align2d/hls"><\/item>
<item  id="1861" filename="batch_align2d_hls/align2d.c" linenumber="33" name="tmp_56_cast1" contextFuncName="compute_inverse_hessian" moduleName="batch_align2D" rtlName="tmp_56_cast1_fu_4518_p1" latency="0" BRAM="-1" DSP="-1" FF="-1" LUT="-1" fileDirectory="/home/dmalvezzi/batch_align2d/hls"><\/item>
<item  id="1862" filename="batch_align2d_hls/align2d.c" linenumber="33" name="tmp_56_cast" contextFuncName="compute_inverse_hessian" moduleName="batch_align2D" rtlName="tmp_56_cast_fu_4522_p1" latency="0" BRAM="-1" DSP="-1" FF="-1" LUT="-1" fileDirectory="/home/dmalvezzi/batch_align2d/hls"><\/item>
<item  id="1863" filename="batch_align2d_hls/align2d.c" linenumber="33" name="tmp13" contextFuncName="compute_inverse_hessian" moduleName="batch_align2D" rtlName="tmp13_fu_4526_p2" latency="0" BRAM="-1" DSP="-1" FF="0" LUT="15" fileDirectory="/home/dmalvezzi/batch_align2d/hls"><\/item>
<item  id="1864" filename="batch_align2d_hls/align2d.c" linenumber="33" name="tmp37_cast" contextFuncName="compute_inverse_hessian" moduleName="batch_align2D" rtlName="tmp37_cast_fu_4532_p1" latency="0" BRAM="-1" DSP="-1" FF="-1" LUT="-1" fileDirectory="/home/dmalvezzi/batch_align2d/hls"><\/item>
<item  id="1865" filename="batch_align2d_hls/align2d.c" linenumber="33" name="tmp_62_t" contextFuncName="compute_inverse_hessian" moduleName="batch_align2D" rtlName="tmp_62_t_fu_4536_p2" latency="0" BRAM="-1" DSP="-1" FF="0" LUT="15" fileDirectory="/home/dmalvezzi/batch_align2d/hls"><\/item>
<item  id="1866" filename="batch_align2d_hls/align2d.c" linenumber="33" name="tmp_38" contextFuncName="compute_inverse_hessian" moduleName="batch_align2D" rtlName="tmp_38_fu_4542_p1" latency="0" BRAM="-1" DSP="-1" FF="-1" LUT="-1" fileDirectory="/home/dmalvezzi/batch_align2d/hls"><\/item>
<item  id="1867" filename="batch_align2d_hls/align2d.c" linenumber="33" name="tmp_39" contextFuncName="compute_inverse_hessian" moduleName="batch_align2D" rtlName="tmp_40_fu_5799_p401" latency="0" BRAM="-1" DSP="-1" FF="0" LUT="16" fileDirectory="/home/dmalvezzi/batch_align2d/hls"><\/item>
<item  id="2180" filename="batch_align2d_hls/align2d.c" linenumber="33" name="tmp_40" contextFuncName="compute_inverse_hessian" moduleName="batch_align2D" rtlName="batch_align2D_mux_4009_8_1_1_U11" latency="0" BRAM="-1" DSP="-1" FF="-1" LUT="-1" fileDirectory="/home/dmalvezzi/batch_align2d/hls"><\/item>
<item  id="2181" filename="batch_align2d_hls/align2d.c" linenumber="33" name="tmp_40_cast" contextFuncName="compute_inverse_hessian" moduleName="batch_align2D" rtlName="tmp_40_cast_fu_6605_p1" latency="0" BRAM="-1" DSP="-1" FF="-1" LUT="-1" fileDirectory="/home/dmalvezzi/batch_align2d/hls"><\/item>
<item  id="2182" filename="batch_align2d_hls/align2d.c" linenumber="33" name="tmp38" contextFuncName="compute_inverse_hessian" moduleName="batch_align2D" rtlName="tmp38_fu_6609_p2" latency="0" BRAM="-1" DSP="-1" FF="0" LUT="15" fileDirectory="/home/dmalvezzi/batch_align2d/hls"><\/item>
<item  id="2183" filename="batch_align2d_hls/align2d.c" linenumber="33" name="tmp38_cast" contextFuncName="compute_inverse_hessian" moduleName="batch_align2D" rtlName="tmp38_cast_fu_6615_p1" latency="0" BRAM="-1" DSP="-1" FF="-1" LUT="-1" fileDirectory="/home/dmalvezzi/batch_align2d/hls"><\/item>
<item  id="2184" filename="batch_align2d_hls/align2d.c" linenumber="33" name="tmp_66_t" contextFuncName="compute_inverse_hessian" moduleName="batch_align2D" rtlName="tmp_66_t_fu_6619_p2" latency="0" BRAM="-1" DSP="-1" FF="0" LUT="15" fileDirectory="/home/dmalvezzi/batch_align2d/hls"><\/item>
<item  id="2185" filename="batch_align2d_hls/align2d.c" linenumber="33" name="tmp_45" contextFuncName="compute_inverse_hessian" moduleName="batch_align2D" rtlName="tmp_45_fu_6625_p1" latency="0" BRAM="-1" DSP="-1" FF="-1" LUT="-1" fileDirectory="/home/dmalvezzi/batch_align2d/hls"><\/item>
<item  id="2186" filename="batch_align2d_hls/align2d.c" linenumber="33" name="tmp_47" contextFuncName="compute_inverse_hessian" moduleName="batch_align2D" rtlName="tmp_51_fu_6666_p401" latency="0" BRAM="-1" DSP="-1" FF="0" LUT="16" fileDirectory="/home/dmalvezzi/batch_align2d/hls"><\/item>
<item  id="2195" filename="batch_align2d_hls/align2d.c" linenumber="33" name="tmp_51" contextFuncName="compute_inverse_hessian" moduleName="batch_align2D" rtlName="batch_align2D_mux_4009_8_1_1_U12" latency="0" BRAM="-1" DSP="-1" FF="-1" LUT="-1" fileDirectory="/home/dmalvezzi/batch_align2d/hls"><\/item>
<item  id="2196" filename="batch_align2d_hls/align2d.c" linenumber="33" name="tmp_64_cast" contextFuncName="compute_inverse_hessian" moduleName="batch_align2D" rtlName="tmp_64_cast_fu_7472_p1" latency="0" BRAM="-1" DSP="-1" FF="-1" LUT="-1" fileDirectory="/home/dmalvezzi/batch_align2d/hls"><\/item>
<item  id="2197" filename="batch_align2d_hls/align2d.c" linenumber="33" name="tmp_54" contextFuncName="compute_inverse_hessian" moduleName="batch_align2D" rtlName="tmp_54_fu_7476_p2" latency="0" BRAM="-1" DSP="-1" FF="0" LUT="16" fileDirectory="/home/dmalvezzi/batch_align2d/hls"><\/item>
<item  id="2198" filename="batch_align2d_hls/align2d.c" linenumber="33" name="tmp_83" contextFuncName="compute_inverse_hessian" moduleName="batch_align2D" rtlName="tmp_83_fu_9474_p1" latency="0" BRAM="-1" DSP="-1" FF="-1" LUT="-1" fileDirectory="/home/dmalvezzi/batch_align2d/hls"><\/item>
<item  id="2199" filename="batch_align2d_hls/align2d.c" linenumber="33" name="tmp_56" contextFuncName="compute_inverse_hessian" moduleName="batch_align2D" rtlName="batch_align2D_sitofp_32s_32_3_1_U9" latency="2" BRAM="-1" DSP="-1" FF="-1" LUT="-1" fileDirectory="/home/dmalvezzi/batch_align2d/hls"><\/item>
<item  id="2200" filename="batch_align2d_hls/align2d.c" linenumber="34" name="tmp39" contextFuncName="compute_inverse_hessian" moduleName="batch_align2D" rtlName="tmp39_fu_7482_p2" latency="0" BRAM="-1" DSP="-1" FF="0" LUT="15" fileDirectory="/home/dmalvezzi/batch_align2d/hls"><\/item>
<item  id="2201" filename="batch_align2d_hls/align2d.c" linenumber="34" name="tmp39_cast" contextFuncName="compute_inverse_hessian" moduleName="batch_align2D" rtlName="tmp39_cast_fu_7488_p1" latency="0" BRAM="-1" DSP="-1" FF="-1" LUT="-1" fileDirectory="/home/dmalvezzi/batch_align2d/hls"><\/item>
<item  id="2202" filename="batch_align2d_hls/align2d.c" linenumber="34" name="tmp_73_t" contextFuncName="compute_inverse_hessian" moduleName="batch_align2D" rtlName="tmp_73_t_fu_7492_p2" latency="0" BRAM="-1" DSP="-1" FF="0" LUT="15" fileDirectory="/home/dmalvezzi/batch_align2d/hls"><\/item>
<item  id="2203" filename="batch_align2d_hls/align2d.c" linenumber="34" name="tmp_60" contextFuncName="compute_inverse_hessian" moduleName="batch_align2D" rtlName="tmp_60_fu_7498_p1" latency="0" BRAM="-1" DSP="-1" FF="-1" LUT="-1" fileDirectory="/home/dmalvezzi/batch_align2d/hls"><\/item>
<item  id="2204" filename="batch_align2d_hls/align2d.c" linenumber="34" name="tmp_62" contextFuncName="compute_inverse_hessian" moduleName="batch_align2D" rtlName="tmp_63_fu_7651_p401" latency="0" BRAM="-1" DSP="-1" FF="0" LUT="16" fileDirectory="/home/dmalvezzi/batch_align2d/hls"><\/item>
<item  id="2241" filename="batch_align2d_hls/align2d.c" linenumber="34" name="tmp_63" contextFuncName="compute_inverse_hessian" moduleName="batch_align2D" rtlName="batch_align2D_mux_4009_8_1_1_U13" latency="0" BRAM="-1" DSP="-1" FF="-1" LUT="-1" fileDirectory="/home/dmalvezzi/batch_align2d/hls"><\/item>
<item  id="2242" filename="batch_align2d_hls/align2d.c" linenumber="34" name="tmp_70_cast" contextFuncName="compute_inverse_hessian" moduleName="batch_align2D" rtlName="tmp_70_cast_fu_8457_p1" latency="0" BRAM="-1" DSP="-1" FF="-1" LUT="-1" fileDirectory="/home/dmalvezzi/batch_align2d/hls"><\/item>
<item  id="2243" filename="batch_align2d_hls/align2d.c" linenumber="33" name="tmp_64" contextFuncName="compute_inverse_hessian" moduleName="batch_align2D" rtlName="tmp_64_fu_8461_p2" latency="0" BRAM="-1" DSP="-1" FF="0" LUT="7" fileDirectory="/home/dmalvezzi/batch_align2d/hls"><\/item>
<item  id="2244" filename="batch_align2d_hls/align2d.c" linenumber="34" name="tmp_77_t" contextFuncName="compute_inverse_hessian" moduleName="batch_align2D" rtlName="tmp_77_t_fu_8467_p2" latency="0" BRAM="-1" DSP="-1" FF="0" LUT="15" fileDirectory="/home/dmalvezzi/batch_align2d/hls"><\/item>
<item  id="2245" filename="batch_align2d_hls/align2d.c" linenumber="34" name="tmp_65" contextFuncName="compute_inverse_hessian" moduleName="batch_align2D" rtlName="tmp_65_fu_8473_p1" latency="0" BRAM="-1" DSP="-1" FF="-1" LUT="-1" fileDirectory="/home/dmalvezzi/batch_align2d/hls"><\/item>
<item  id="2246" filename="batch_align2d_hls/align2d.c" linenumber="34" name="tmp_66" contextFuncName="compute_inverse_hessian" moduleName="batch_align2D" rtlName="tmp_67_fu_8658_p401" latency="0" BRAM="-1" DSP="-1" FF="0" LUT="16" fileDirectory="/home/dmalvezzi/batch_align2d/hls"><\/item>
<item  id="2291" filename="batch_align2d_hls/align2d.c" linenumber="34" name="tmp_67" contextFuncName="compute_inverse_hessian" moduleName="batch_align2D" rtlName="batch_align2D_mux_4009_8_1_1_U14" latency="0" BRAM="-1" DSP="-1" FF="-1" LUT="-1" fileDirectory="/home/dmalvezzi/batch_align2d/hls"><\/item>
<item  id="2292" filename="batch_align2d_hls/align2d.c" linenumber="34" name="tmp_75_cast" contextFuncName="compute_inverse_hessian" moduleName="batch_align2D" rtlName="tmp_75_cast_fu_9464_p1" latency="0" BRAM="-1" DSP="-1" FF="-1" LUT="-1" fileDirectory="/home/dmalvezzi/batch_align2d/hls"><\/item>
<item  id="2293" filename="batch_align2d_hls/align2d.c" linenumber="34" name="tmp_68" contextFuncName="compute_inverse_hessian" moduleName="batch_align2D" rtlName="tmp_68_fu_9468_p2" latency="0" BRAM="-1" DSP="-1" FF="0" LUT="16" fileDirectory="/home/dmalvezzi/batch_align2d/hls"><\/item>
<item  id="2294" filename="batch_align2d_hls/align2d.c" linenumber="34" name="tmp_84" contextFuncName="compute_inverse_hessian" moduleName="batch_align2D" rtlName="grp_fu_1757_p0" latency="0" BRAM="-1" DSP="-1" FF="-1" LUT="-1" fileDirectory="/home/dmalvezzi/batch_align2d/hls"><\/item>
<item  id="2295" filename="batch_align2d_hls/align2d.c" linenumber="34" name="tmp_69" contextFuncName="compute_inverse_hessian" moduleName="batch_align2D" rtlName="batch_align2D_sitofp_32s_32_3_1_U10" latency="2" BRAM="-1" DSP="-1" FF="-1" LUT="-1" fileDirectory="/home/dmalvezzi/batch_align2d/hls"><\/item>
<item  id="2296" filename="batch_align2d_hls/align2d.c" linenumber="40" name="tmp_70" contextFuncName="compute_inverse_hessian" moduleName="batch_align2D" rtlName="batch_align2D_fmul_32ns_32ns_32_2_max_dsp_1_U4" latency="1" BRAM="-1" DSP="-1" FF="-1" LUT="-1" fileDirectory="/home/dmalvezzi/batch_align2d/hls"><\/item>
<item  id="2297" filename="batch_align2d_hls/align2d.c" linenumber="40" name="tmp_71" contextFuncName="compute_inverse_hessian" moduleName="batch_align2D" rtlName="batch_align2D_faddfsub_32ns_32ns_32_4_full_dsp_1_U1" latency="3" BRAM="-1" DSP="-1" FF="-1" LUT="-1" fileDirectory="/home/dmalvezzi/batch_align2d/hls"><\/item>
<item  id="2298" filename="batch_align2d_hls/align2d.c" linenumber="41" name="tmp_72" contextFuncName="compute_inverse_hessian" moduleName="batch_align2D" rtlName="batch_align2D_fmul_32ns_32ns_32_2_max_dsp_1_U5" latency="1" BRAM="-1" DSP="-1" FF="-1" LUT="-1" fileDirectory="/home/dmalvezzi/batch_align2d/hls"><\/item>
<item  id="2299" filename="batch_align2d_hls/align2d.c" linenumber="41" name="tmp_73" contextFuncName="compute_inverse_hessian" moduleName="batch_align2D" rtlName="batch_align2D_faddfsub_32ns_32ns_32_4_full_dsp_1_U2" latency="3" BRAM="-1" DSP="-1" FF="-1" LUT="-1" fileDirectory="/home/dmalvezzi/batch_align2d/hls"><\/item>
<item  id="2300" filename="batch_align2d_hls/align2d.c" linenumber="42" name="tmp_74" contextFuncName="compute_inverse_hessian" moduleName="batch_align2D" rtlName="batch_align2D_faddfsub_32ns_32ns_32_4_full_dsp_1_U1" latency="3" BRAM="-1" DSP="-1" FF="-1" LUT="-1" fileDirectory="/home/dmalvezzi/batch_align2d/hls"><\/item>
<item  id="2301" filename="batch_align2d_hls/align2d.c" linenumber="43" name="tmp_75" contextFuncName="compute_inverse_hessian" moduleName="batch_align2D" rtlName="batch_align2D_fmul_32ns_32ns_32_2_max_dsp_1_U6" latency="1" BRAM="-1" DSP="-1" FF="-1" LUT="-1" fileDirectory="/home/dmalvezzi/batch_align2d/hls"><\/item>
<item  id="2302" filename="batch_align2d_hls/align2d.c" linenumber="43" name="tmp_76" contextFuncName="compute_inverse_hessian" moduleName="batch_align2D" rtlName="batch_align2D_fadd_32ns_32ns_32_4_full_dsp_1_U3" latency="3" BRAM="-1" DSP="-1" FF="-1" LUT="-1" fileDirectory="/home/dmalvezzi/batch_align2d/hls"><\/item>
<item  id="2303" filename="batch_align2d_hls/align2d.c" linenumber="44" name="tmp_77" contextFuncName="compute_inverse_hessian" moduleName="batch_align2D" rtlName="batch_align2D_faddfsub_32ns_32ns_32_4_full_dsp_1_U2" latency="3" BRAM="-1" DSP="-1" FF="-1" LUT="-1" fileDirectory="/home/dmalvezzi/batch_align2d/hls"><\/item>
<item  id="2306" filename="batch_align2d_hls/align2d.c" linenumber="50" name="tmp_12" contextFuncName="compute_inverse_hessian" moduleName="batch_align2D" rtlName="batch_align2D_fmul_32ns_32ns_32_2_max_dsp_1_U4" latency="1" BRAM="-1" DSP="-1" FF="-1" LUT="-1" fileDirectory="/home/dmalvezzi/batch_align2d/hls"><\/item>
<item  id="2307" filename="batch_align2d_hls/align2d.c" linenumber="51" name="tmp_13" contextFuncName="compute_inverse_hessian" moduleName="batch_align2D" rtlName="batch_align2D_fmul_32ns_32ns_32_2_max_dsp_1_U4" latency="1" BRAM="-1" DSP="-1" FF="-1" LUT="-1" fileDirectory="/home/dmalvezzi/batch_align2d/hls"><\/item>
<item  id="2308" filename="batch_align2d_hls/align2d.c" linenumber="52" name="tmp_14" contextFuncName="compute_inverse_hessian" moduleName="batch_align2D" rtlName="batch_align2D_fmul_32ns_32ns_32_2_max_dsp_1_U5" latency="1" BRAM="-1" DSP="-1" FF="-1" LUT="-1" fileDirectory="/home/dmalvezzi/batch_align2d/hls"><\/item>
<item  id="2309" filename="batch_align2d_hls/align2d.c" linenumber="53" name="tmp_15" contextFuncName="compute_inverse_hessian" moduleName="batch_align2D" rtlName="batch_align2D_fmul_32ns_32ns_32_2_max_dsp_1_U5" latency="1" BRAM="-1" DSP="-1" FF="-1" LUT="-1" fileDirectory="/home/dmalvezzi/batch_align2d/hls"><\/item>
<item  id="2310" filename="batch_align2d_hls/align2d.c" linenumber="54" name="tmp_16" contextFuncName="compute_inverse_hessian" moduleName="batch_align2D" rtlName="batch_align2D_fmul_32ns_32ns_32_2_max_dsp_1_U6" latency="1" BRAM="-1" DSP="-1" FF="-1" LUT="-1" fileDirectory="/home/dmalvezzi/batch_align2d/hls"><\/item>
<item  id="2311" filename="batch_align2d_hls/align2d.c" linenumber="68" name="tmp_17" contextFuncName="compute_inverse_hessian" moduleName="batch_align2D" rtlName="batch_align2D_fmul_32ns_32ns_32_2_max_dsp_1_U4" latency="1" BRAM="-1" DSP="-1" FF="-1" LUT="-1" fileDirectory="/home/dmalvezzi/batch_align2d/hls"><\/item>
<item  id="2312" filename="batch_align2d_hls/align2d.c" linenumber="68" name="tmp_18" contextFuncName="compute_inverse_hessian" moduleName="batch_align2D" rtlName="batch_align2D_fmul_32ns_32ns_32_2_max_dsp_1_U4" latency="1" BRAM="-1" DSP="-1" FF="-1" LUT="-1" fileDirectory="/home/dmalvezzi/batch_align2d/hls"><\/item>
<item  id="2313" filename="batch_align2d_hls/align2d.c" linenumber="68" name="tmp_19" contextFuncName="compute_inverse_hessian" moduleName="batch_align2D" rtlName="batch_align2D_fmul_32ns_32ns_32_2_max_dsp_1_U4" latency="1" BRAM="-1" DSP="-1" FF="-1" LUT="-1" fileDirectory="/home/dmalvezzi/batch_align2d/hls"><\/item>
<item  id="2314" filename="batch_align2d_hls/align2d.c" linenumber="68" name="tmp_20" contextFuncName="compute_inverse_hessian" moduleName="batch_align2D" rtlName="batch_align2D_fmul_32ns_32ns_32_2_max_dsp_1_U6" latency="1" BRAM="-1" DSP="-1" FF="-1" LUT="-1" fileDirectory="/home/dmalvezzi/batch_align2d/hls"><\/item>
<item  id="2315" filename="batch_align2d_hls/align2d.c" linenumber="68" name="tmp_21" contextFuncName="compute_inverse_hessian" moduleName="batch_align2D" rtlName="batch_align2D_fmul_32ns_32ns_32_2_max_dsp_1_U5" latency="1" BRAM="-1" DSP="-1" FF="-1" LUT="-1" fileDirectory="/home/dmalvezzi/batch_align2d/hls"><\/item>
<item  id="2316" filename="batch_align2d_hls/align2d.c" linenumber="68" name="tmp_22" contextFuncName="compute_inverse_hessian" moduleName="batch_align2D" rtlName="batch_align2D_fmul_32ns_32ns_32_2_max_dsp_1_U7" latency="1" BRAM="-1" DSP="-1" FF="-1" LUT="-1" fileDirectory="/home/dmalvezzi/batch_align2d/hls"><\/item>
<item  id="2317" filename="batch_align2d_hls/align2d.c" linenumber="68" name="tmp7" contextFuncName="compute_inverse_hessian" moduleName="batch_align2D" rtlName="batch_align2D_faddfsub_32ns_32ns_32_4_full_dsp_1_U1" latency="3" BRAM="-1" DSP="-1" FF="-1" LUT="-1" fileDirectory="/home/dmalvezzi/batch_align2d/hls"><\/item>
<item  id="2318" filename="batch_align2d_hls/align2d.c" linenumber="68" name="tmp_23" contextFuncName="compute_inverse_hessian" moduleName="batch_align2D" rtlName="batch_align2D_faddfsub_32ns_32ns_32_4_full_dsp_1_U1" latency="3" BRAM="-1" DSP="-1" FF="-1" LUT="-1" fileDirectory="/home/dmalvezzi/batch_align2d/hls"><\/item>
<item  id="2319" filename="batch_align2d_hls/align2d.c" linenumber="68" name="tmp_24" contextFuncName="compute_inverse_hessian" moduleName="batch_align2D" rtlName="batch_align2D_fmul_32ns_32ns_32_2_max_dsp_1_U4" latency="1" BRAM="-1" DSP="-1" FF="-1" LUT="-1" fileDirectory="/home/dmalvezzi/batch_align2d/hls"><\/item>
<item  id="2320" filename="batch_align2d_hls/align2d.c" linenumber="68" name="tmp_25" contextFuncName="compute_inverse_hessian" moduleName="batch_align2D" rtlName="batch_align2D_fmul_32ns_32ns_32_2_max_dsp_1_U4" latency="1" BRAM="-1" DSP="-1" FF="-1" LUT="-1" fileDirectory="/home/dmalvezzi/batch_align2d/hls"><\/item>
<item  id="2321" filename="batch_align2d_hls/align2d.c" linenumber="68" name="tmp_26" contextFuncName="compute_inverse_hessian" moduleName="batch_align2D" rtlName="batch_align2D_faddfsub_32ns_32ns_32_4_full_dsp_1_U1" latency="3" BRAM="-1" DSP="-1" FF="-1" LUT="-1" fileDirectory="/home/dmalvezzi/batch_align2d/hls"><\/item>
<item  id="2322" filename="batch_align2d_hls/align2d.c" linenumber="68" name="tmp_27" contextFuncName="compute_inverse_hessian" moduleName="batch_align2D" rtlName="batch_align2D_fmul_32ns_32ns_32_2_max_dsp_1_U4" latency="1" BRAM="-1" DSP="-1" FF="-1" LUT="-1" fileDirectory="/home/dmalvezzi/batch_align2d/hls"><\/item>
<item  id="2323" filename="batch_align2d_hls/align2d.c" linenumber="68" name="tmp_28" contextFuncName="compute_inverse_hessian" moduleName="batch_align2D" rtlName="batch_align2D_fmul_32ns_32ns_32_2_max_dsp_1_U4" latency="1" BRAM="-1" DSP="-1" FF="-1" LUT="-1" fileDirectory="/home/dmalvezzi/batch_align2d/hls"><\/item>
<item  id="2324" filename="batch_align2d_hls/align2d.c" linenumber="68" name="tmp_29" contextFuncName="compute_inverse_hessian" moduleName="batch_align2D" rtlName="batch_align2D_faddfsub_32ns_32ns_32_4_full_dsp_1_U1" latency="3" BRAM="-1" DSP="-1" FF="-1" LUT="-1" fileDirectory="/home/dmalvezzi/batch_align2d/hls"><\/item>
<item  id="2325" filename="batch_align2d_hls/align2d.c" linenumber="68" name="tmp_30" contextFuncName="compute_inverse_hessian" moduleName="batch_align2D" rtlName="batch_align2D_fmul_32ns_32ns_32_2_max_dsp_1_U4" latency="1" BRAM="-1" DSP="-1" FF="-1" LUT="-1" fileDirectory="/home/dmalvezzi/batch_align2d/hls"><\/item>
<item  id="2326" filename="batch_align2d_hls/align2d.c" linenumber="68" name="tmp_31" contextFuncName="compute_inverse_hessian" moduleName="batch_align2D" rtlName="batch_align2D_fmul_32ns_32ns_32_2_max_dsp_1_U4" latency="1" BRAM="-1" DSP="-1" FF="-1" LUT="-1" fileDirectory="/home/dmalvezzi/batch_align2d/hls"><\/item>
<item  id="2327" filename="batch_align2d_hls/align2d.c" linenumber="68" name="det" contextFuncName="compute_inverse_hessian" moduleName="batch_align2D" rtlName="batch_align2D_faddfsub_32ns_32ns_32_4_full_dsp_1_U1" latency="3" BRAM="-1" DSP="-1" FF="-1" LUT="-1" fileDirectory="/home/dmalvezzi/batch_align2d/hls"><\/item>
<item  id="2328" filename="batch_align2d_hls/align2d.c" linenumber="70" name="tmp_32" contextFuncName="compute_inverse_hessian" moduleName="batch_align2D" rtlName="batch_align2D_fmul_32ns_32ns_32_2_max_dsp_1_U5" latency="1" BRAM="-1" DSP="-1" FF="-1" LUT="-1" fileDirectory="/home/dmalvezzi/batch_align2d/hls"><\/item>
<item  id="2329" filename="batch_align2d_hls/align2d.c" linenumber="70" name="tmp_33" contextFuncName="compute_inverse_hessian" moduleName="batch_align2D" rtlName="batch_align2D_fmul_32ns_32ns_32_2_max_dsp_1_U6" latency="1" BRAM="-1" DSP="-1" FF="-1" LUT="-1" fileDirectory="/home/dmalvezzi/batch_align2d/hls"><\/item>
<item  id="2330" filename="batch_align2d_hls/align2d.c" linenumber="70" name="tmp_34" contextFuncName="compute_inverse_hessian" moduleName="batch_align2D" rtlName="batch_align2D_faddfsub_32ns_32ns_32_4_full_dsp_1_U2" latency="3" BRAM="-1" DSP="-1" FF="-1" LUT="-1" fileDirectory="/home/dmalvezzi/batch_align2d/hls"><\/item>
<item  id="2331" filename="batch_align2d_hls/align2d.c" linenumber="70" name="H_inv_0_0" contextFuncName="compute_inverse_hessian" moduleName="batch_align2D" rtlName="batch_align2D_fdiv_32ns_32ns_32_8_1_U8" latency="7" BRAM="-1" DSP="-1" FF="-1" LUT="-1" fileDirectory="/home/dmalvezzi/batch_align2d/hls"><\/item>
<item  id="2346" filename="batch_align2d_hls/align2d.c" linenumber="71" name="tmp_41" contextFuncName="compute_inverse_hessian" moduleName="batch_align2D" rtlName="batch_align2D_fmul_32ns_32ns_32_2_max_dsp_1_U4" latency="1" BRAM="-1" DSP="-1" FF="-1" LUT="-1" fileDirectory="/home/dmalvezzi/batch_align2d/hls"><\/item>
<item  id="2347" filename="batch_align2d_hls/align2d.c" linenumber="71" name="tmp_42" contextFuncName="compute_inverse_hessian" moduleName="batch_align2D" rtlName="batch_align2D_fmul_32ns_32ns_32_2_max_dsp_1_U5" latency="1" BRAM="-1" DSP="-1" FF="-1" LUT="-1" fileDirectory="/home/dmalvezzi/batch_align2d/hls"><\/item>
<item  id="2348" filename="batch_align2d_hls/align2d.c" linenumber="71" name="tmp_43" contextFuncName="compute_inverse_hessian" moduleName="batch_align2D" rtlName="batch_align2D_faddfsub_32ns_32ns_32_4_full_dsp_1_U1" latency="3" BRAM="-1" DSP="-1" FF="-1" LUT="-1" fileDirectory="/home/dmalvezzi/batch_align2d/hls"><\/item>
<item  id="2349" filename="batch_align2d_hls/align2d.c" linenumber="71" name="tmp_44_to_int" contextFuncName="compute_inverse_hessian" moduleName="batch_align2D" rtlName="tmp_44_to_int_fu_9502_p1" latency="0" BRAM="-1" DSP="-1" FF="-1" LUT="-1" fileDirectory="/home/dmalvezzi/batch_align2d/hls"><\/item>
<item  id="2350" filename="batch_align2d_hls/align2d.c" linenumber="71" name="tmp_44_neg" contextFuncName="compute_inverse_hessian" moduleName="batch_align2D" rtlName="tmp_44_neg_fu_9506_p2" latency="0" BRAM="-1" DSP="-1" FF="0" LUT="33" fileDirectory="/home/dmalvezzi/batch_align2d/hls"><\/item>
<item  id="2351" filename="batch_align2d_hls/align2d.c" linenumber="71" name="tmp_44" contextFuncName="compute_inverse_hessian" moduleName="batch_align2D" rtlName="tmp_44_fu_9512_p1" latency="0" BRAM="-1" DSP="-1" FF="-1" LUT="-1" fileDirectory="/home/dmalvezzi/batch_align2d/hls"><\/item>
<item  id="2352" filename="batch_align2d_hls/align2d.c" linenumber="71" name="H_inv_0_3" contextFuncName="compute_inverse_hessian" moduleName="batch_align2D" rtlName="batch_align2D_fdiv_32ns_32ns_32_8_1_U8" latency="7" BRAM="-1" DSP="-1" FF="-1" LUT="-1" fileDirectory="/home/dmalvezzi/batch_align2d/hls"><\/item>
<item  id="2367" filename="batch_align2d_hls/align2d.c" linenumber="72" name="tmp_46" contextFuncName="compute_inverse_hessian" moduleName="batch_align2D" rtlName="batch_align2D_faddfsub_32ns_32ns_32_4_full_dsp_1_U1" latency="3" BRAM="-1" DSP="-1" FF="-1" LUT="-1" fileDirectory="/home/dmalvezzi/batch_align2d/hls"><\/item>
<item  id="2368" filename="batch_align2d_hls/align2d.c" linenumber="72" name="H_inv_0_6" contextFuncName="compute_inverse_hessian" moduleName="batch_align2D" rtlName="batch_align2D_fdiv_32ns_32ns_32_8_1_U8" latency="7" BRAM="-1" DSP="-1" FF="-1" LUT="-1" fileDirectory="/home/dmalvezzi/batch_align2d/hls"><\/item>
<item  id="2397" filename="batch_align2d_hls/align2d.c" linenumber="75" name="tmp_48" contextFuncName="compute_inverse_hessian" moduleName="batch_align2D" rtlName="batch_align2D_fmul_32ns_32ns_32_2_max_dsp_1_U4" latency="1" BRAM="-1" DSP="-1" FF="-1" LUT="-1" fileDirectory="/home/dmalvezzi/batch_align2d/hls"><\/item>
<item  id="2398" filename="batch_align2d_hls/align2d.c" linenumber="75" name="tmp_49" contextFuncName="compute_inverse_hessian" moduleName="batch_align2D" rtlName="batch_align2D_fmul_32ns_32ns_32_2_max_dsp_1_U5" latency="1" BRAM="-1" DSP="-1" FF="-1" LUT="-1" fileDirectory="/home/dmalvezzi/batch_align2d/hls"><\/item>
<item  id="2399" filename="batch_align2d_hls/align2d.c" linenumber="75" name="tmp_50" contextFuncName="compute_inverse_hessian" moduleName="batch_align2D" rtlName="batch_align2D_faddfsub_32ns_32ns_32_4_full_dsp_1_U1" latency="3" BRAM="-1" DSP="-1" FF="-1" LUT="-1" fileDirectory="/home/dmalvezzi/batch_align2d/hls"><\/item>
<item  id="2400" filename="batch_align2d_hls/align2d.c" linenumber="75" name="H_inv_0_4" contextFuncName="compute_inverse_hessian" moduleName="batch_align2D" rtlName="batch_align2D_fdiv_32ns_32ns_32_8_1_U8" latency="7" BRAM="-1" DSP="-1" FF="-1" LUT="-1" fileDirectory="/home/dmalvezzi/batch_align2d/hls"><\/item>
<item  id="2415" filename="batch_align2d_hls/align2d.c" linenumber="76" name="tmp_52" contextFuncName="compute_inverse_hessian" moduleName="batch_align2D" rtlName="batch_align2D_faddfsub_32ns_32ns_32_4_full_dsp_1_U1" latency="3" BRAM="-1" DSP="-1" FF="-1" LUT="-1" fileDirectory="/home/dmalvezzi/batch_align2d/hls"><\/item>
<item  id="2416" filename="batch_align2d_hls/align2d.c" linenumber="76" name="tmp_53_to_int" contextFuncName="compute_inverse_hessian" moduleName="batch_align2D" rtlName="tmp_53_to_int_fu_9597_p1" latency="0" BRAM="-1" DSP="-1" FF="-1" LUT="-1" fileDirectory="/home/dmalvezzi/batch_align2d/hls"><\/item>
<item  id="2417" filename="batch_align2d_hls/align2d.c" linenumber="76" name="tmp_53_neg" contextFuncName="compute_inverse_hessian" moduleName="batch_align2D" rtlName="tmp_53_neg_fu_9601_p2" latency="0" BRAM="-1" DSP="-1" FF="0" LUT="33" fileDirectory="/home/dmalvezzi/batch_align2d/hls"><\/item>
<item  id="2418" filename="batch_align2d_hls/align2d.c" linenumber="76" name="tmp_53" contextFuncName="compute_inverse_hessian" moduleName="batch_align2D" rtlName="tmp_53_fu_9607_p1" latency="0" BRAM="-1" DSP="-1" FF="-1" LUT="-1" fileDirectory="/home/dmalvezzi/batch_align2d/hls"><\/item>
<item  id="2419" filename="batch_align2d_hls/align2d.c" linenumber="76" name="H_inv_0_7" contextFuncName="compute_inverse_hessian" moduleName="batch_align2D" rtlName="batch_align2D_fdiv_32ns_32ns_32_8_1_U8" latency="7" BRAM="-1" DSP="-1" FF="-1" LUT="-1" fileDirectory="/home/dmalvezzi/batch_align2d/hls"><\/item>
<item  id="2462" filename="batch_align2d_hls/align2d.c" linenumber="80" name="tmp_55" contextFuncName="compute_inverse_hessian" moduleName="batch_align2D" rtlName="batch_align2D_faddfsub_32ns_32ns_32_4_full_dsp_1_U1" latency="3" BRAM="-1" DSP="-1" FF="-1" LUT="-1" fileDirectory="/home/dmalvezzi/batch_align2d/hls"><\/item>
<item  id="2463" filename="batch_align2d_hls/align2d.c" linenumber="80" name="H_inv_0_8" contextFuncName="compute_inverse_hessian" moduleName="batch_align2D" rtlName="batch_align2D_fdiv_32ns_32ns_32_8_1_U8" latency="7" BRAM="-1" DSP="-1" FF="-1" LUT="-1" fileDirectory="/home/dmalvezzi/batch_align2d/hls"><\/item>
<item  id="2480" filename="batch_align2d_hls/align2d.c" linenumber="174" name="tmp_57" contextFuncName="batch_align2D" moduleName="batch_align2D" rtlName="tmp_57_fu_9719_p1" latency="0" BRAM="-1" DSP="-1" FF="-1" LUT="-1" fileDirectory="/home/dmalvezzi/batch_align2d/hls"><\/item>
<item  id="2481" filename="batch_align2d_hls/align2d.c" linenumber="174" name="tmp_58" contextFuncName="batch_align2D" moduleName="batch_align2D" rtlName="batch_align2D_sitofp_32s_32_3_1_U9" latency="2" BRAM="-1" DSP="-1" FF="-1" LUT="-1" fileDirectory="/home/dmalvezzi/batch_align2d/hls"><\/item>
<item  id="2482" filename="batch_align2d_hls/align2d.c" linenumber="174" name="tmp_59" contextFuncName="batch_align2D" moduleName="batch_align2D" rtlName="batch_align2D_faddfsub_32ns_32ns_32_4_full_dsp_1_U1" latency="3" BRAM="-1" DSP="-1" FF="-1" LUT="-1" fileDirectory="/home/dmalvezzi/batch_align2d/hls"><\/item>
<item  id="2483" filename="batch_align2d_hls/align2d.c" linenumber="151" name="tmp_80" contextFuncName="batch_align2D" moduleName="batch_align2D" rtlName="tmp_80_fu_9692_p3" latency="0" BRAM="-1" DSP="-1" FF="-1" LUT="-1" fileDirectory="/home/dmalvezzi/batch_align2d/hls"><\/item>
<item  id="2484" filename="batch_align2d_hls/align2d.c" linenumber="174" name="tmp_81_cast" contextFuncName="batch_align2D" moduleName="batch_align2D" rtlName="tmp_81_cast_fu_9700_p1" latency="0" BRAM="-1" DSP="-1" FF="-1" LUT="-1" fileDirectory="/home/dmalvezzi/batch_align2d/hls"><\/item>
<item  id="2485" filename="batch_align2d_hls/align2d.c" linenumber="174" name="cur_px_estimate_ptr6_1" contextFuncName="batch_align2D" moduleName="batch_align2D" rtlName="cur_px_estimate_ptr6_1_fu_9704_p2" latency="0" BRAM="-1" DSP="-1" FF="0" LUT="70" fileDirectory="/home/dmalvezzi/batch_align2d/hls"><\/item>
<item  id="2486" filename="batch_align2d_hls/align2d.c" linenumber="174" name="cur_px_estimate_ptr6" contextFuncName="batch_align2D" moduleName="batch_align2D" rtlName="cur_px_estimate_ptr6_fu_9709_p1" latency="0" BRAM="-1" DSP="-1" FF="-1" LUT="-1" fileDirectory="/home/dmalvezzi/batch_align2d/hls"><\/item>
<item  id="2498" filename="batch_align2d_hls/align2d.c" linenumber="177" name="exitcond4" contextFuncName="batch_align2D" moduleName="batch_align2D" rtlName="exitcond4_fu_9723_p2" latency="0" BRAM="-1" DSP="-1" FF="0" LUT="11" fileDirectory="/home/dmalvezzi/batch_align2d/hls"><\/item>
<item  id="2500" filename="batch_align2d_hls/align2d.c" linenumber="177" name="indvar_next3" contextFuncName="batch_align2D" moduleName="batch_align2D" rtlName="indvar_next3_fu_9729_p2" latency="0" BRAM="-1" DSP="-1" FF="0" LUT="15" fileDirectory="/home/dmalvezzi/batch_align2d/hls"><\/item>
<item  id="2542" filename="batch_align2d_hls/align2d.c" linenumber="177" name="tmp_11" contextFuncName="batch_align2D" moduleName="batch_align2D" rtlName="batch_align2D_mux_366_32_1_1_U15" latency="0" BRAM="-1" DSP="-1" FF="-1" LUT="-1" fileDirectory="/home/dmalvezzi/batch_align2d/hls"><\/item>
<item  id="2552" filename="batch_align2d_hls/align2d.c" linenumber="180" name="exitcond5" contextFuncName="batch_align2D" moduleName="batch_align2D" rtlName="exitcond5_fu_9921_p2" latency="0" BRAM="-1" DSP="-1" FF="0" LUT="11" fileDirectory="/home/dmalvezzi/batch_align2d/hls"><\/item>
<item  id="2554" filename="batch_align2d_hls/align2d.c" linenumber="180" name="indvar_next4" contextFuncName="batch_align2D" moduleName="batch_align2D" rtlName="indvar_next4_fu_9927_p2" latency="0" BRAM="-1" DSP="-1" FF="0" LUT="12" fileDirectory="/home/dmalvezzi/batch_align2d/hls"><\/item>
<item  id="2560" filename="batch_align2d_hls/align2d.c" linenumber="180" name="tmp_85" contextFuncName="batch_align2D" moduleName="batch_align2D" rtlName="tmp_85_fu_9933_p1" latency="0" BRAM="-1" DSP="-1" FF="-1" LUT="-1" fileDirectory="/home/dmalvezzi/batch_align2d/hls"><\/item>
<item  id="2569" filename="aesl_mux_load.8floatP.i4" linenumber="930" name="sel_tmp_i" contextFuncName="aesl_mux_load.8floatP.i4" moduleName="batch_align2D" rtlName="sel_tmp_i_fu_9969_p2" latency="0" BRAM="-1" DSP="-1" FF="0" LUT="9" fileDirectory="/"><\/item>
<item  id="2570" filename="aesl_mux_load.8floatP.i4" linenumber="928" name="sel_tmp1_i" contextFuncName="aesl_mux_load.8floatP.i4" moduleName="batch_align2D" rtlName="sel_tmp1_i_fu_9975_p3" latency="0" BRAM="-1" DSP="-1" FF="0" LUT="32" fileDirectory="/"><\/item>
<item  id="2571" filename="aesl_mux_load.8floatP.i4" linenumber="930" name="sel_tmp2_i" contextFuncName="aesl_mux_load.8floatP.i4" moduleName="batch_align2D" rtlName="sel_tmp2_i_fu_9983_p2" latency="0" BRAM="-1" DSP="-1" FF="0" LUT="9" fileDirectory="/"><\/item>
<item  id="2572" filename="aesl_mux_load.8floatP.i4" linenumber="928" name="sel_tmp3_i" contextFuncName="aesl_mux_load.8floatP.i4" moduleName="batch_align2D" rtlName="sel_tmp3_i_fu_9989_p3" latency="0" BRAM="-1" DSP="-1" FF="0" LUT="32" fileDirectory="/"><\/item>
<item  id="2573" filename="aesl_mux_load.8floatP.i4" linenumber="930" name="sel_tmp4_i" contextFuncName="aesl_mux_load.8floatP.i4" moduleName="batch_align2D" rtlName="sel_tmp4_i_fu_9997_p2" latency="0" BRAM="-1" DSP="-1" FF="0" LUT="9" fileDirectory="/"><\/item>
<item  id="2574" filename="aesl_mux_load.8floatP.i4" linenumber="928" name="sel_tmp5_i" contextFuncName="aesl_mux_load.8floatP.i4" moduleName="batch_align2D" rtlName="sel_tmp5_i_fu_10003_p3" latency="0" BRAM="-1" DSP="-1" FF="0" LUT="32" fileDirectory="/"><\/item>
<item  id="2575" filename="aesl_mux_load.8floatP.i4" linenumber="930" name="sel_tmp6_i" contextFuncName="aesl_mux_load.8floatP.i4" moduleName="batch_align2D" rtlName="sel_tmp6_i_fu_10011_p2" latency="0" BRAM="-1" DSP="-1" FF="0" LUT="9" fileDirectory="/"><\/item>
<item  id="2576" filename="aesl_mux_load.8floatP.i4" linenumber="928" name="sel_tmp7_i" contextFuncName="aesl_mux_load.8floatP.i4" moduleName="batch_align2D" rtlName="sel_tmp7_i_fu_10017_p3" latency="0" BRAM="-1" DSP="-1" FF="0" LUT="32" fileDirectory="/"><\/item>
<item  id="2577" filename="aesl_mux_load.8floatP.i4" linenumber="930" name="sel_tmp8_i" contextFuncName="aesl_mux_load.8floatP.i4" moduleName="batch_align2D" rtlName="sel_tmp8_i_fu_10025_p2" latency="0" BRAM="-1" DSP="-1" FF="0" LUT="9" fileDirectory="/"><\/item>
<item  id="2578" filename="aesl_mux_load.8floatP.i4" linenumber="928" name="sel_tmp9_i" contextFuncName="aesl_mux_load.8floatP.i4" moduleName="batch_align2D" rtlName="sel_tmp9_i_fu_10031_p3" latency="0" BRAM="-1" DSP="-1" FF="0" LUT="32" fileDirectory="/"><\/item>
<item  id="2579" filename="aesl_mux_load.8floatP.i4" linenumber="930" name="sel_tmp10_i" contextFuncName="aesl_mux_load.8floatP.i4" moduleName="batch_align2D" rtlName="sel_tmp10_i_fu_10039_p2" latency="0" BRAM="-1" DSP="-1" FF="0" LUT="9" fileDirectory="/"><\/item>
<item  id="2580" filename="aesl_mux_load.8floatP.i4" linenumber="928" name="sel_tmp11_i" contextFuncName="aesl_mux_load.8floatP.i4" moduleName="batch_align2D" rtlName="sel_tmp11_i_fu_10045_p3" latency="0" BRAM="-1" DSP="-1" FF="0" LUT="32" fileDirectory="/"><\/item>
<item  id="2581" filename="aesl_mux_load.8floatP.i4" linenumber="930" name="sel_tmp12_i" contextFuncName="aesl_mux_load.8floatP.i4" moduleName="batch_align2D" rtlName="sel_tmp12_i_fu_10053_p2" latency="0" BRAM="-1" DSP="-1" FF="0" LUT="9" fileDirectory="/"><\/item>
<item  id="2582" filename="aesl_mux_load.8floatP.i4" linenumber="928" name="UnifiedRetVal_i" contextFuncName="aesl_mux_load.8floatP.i4" moduleName="batch_align2D" rtlName="UnifiedRetVal_i_fu_10059_p3" latency="0" BRAM="-1" DSP="-1" FF="0" LUT="32" fileDirectory="/"><\/item>
</annotationInfo>
